mlbcolors/__init__.py
mlbcolors/data.json
mlbcolors-0.0.1.dist-info/LICENSE
mlbcolors-0.0.1.dist-info/METADATA
mlbcolors-0.0.1.dist-info/WHEEL
mlbcolors-0.0.1.dist-info/top_level.txt
mlbcolors-0.0.1.dist-info/RECORD
